eig/__init__.py
eig/bayes.py
eig/context.py
eig/eig.py
eig/hypothesis.py
eig/battleship/__init__.py
eig/battleship/hypothesis_cy.cpython-36m-darwin.so
eig/battleship/parser.py
eig/battleship/program.py
eig/battleship/cpp/hypothesis.cc
eig/battleship/cpp/hypothesis.h
eig/battleship/cpp/nodes.cc
eig/battleship/cpp/nodes.h
eig/battleship/cython/__init__.py
eig/battleship/cython/executor.cpython-36m-darwin.so
eig/battleship/cython/executor.pxd
eig/battleship/cython/executor.pyx
eig/battleship/cython/hypothesis.cpython-36m-darwin.so
eig/battleship/cython/hypothesis.pxd
eig/battleship/cython/hypothesis.pyx
eig/battleship/python/__init__.py
eig/battleship/python/executor.py
eig/battleship/python/functions.py
eig/battleship/python/hypothesis.py
eig/battleship/python/priors.py
eig/battleship/question/executor.cpython-36m-darwin.so
expected_information_gain-1.0.3.dist-info/METADATA
expected_information_gain-1.0.3.dist-info/RECORD
expected_information_gain-1.0.3.dist-info/WHEEL
expected_information_gain-1.0.3.dist-info/top_level.txt
