Metadata-Version: 2.1
Name: expected-information-gain
Version: 1.0.3
Summary: Parsing, executing, and calculating expected information gain for program-form questions.
Home-page: https://github.com/anselmrothe/EIG
License: MIT
Platform: UNKNOWN
Requires-Dist: numpy
Requires-Dist: cython
